pimage/__init__.py
pimage/block.py
pimage/configuration.py
pimage/container.py
pimage/copy_move.py
pimage/image_object.py
pimage-1.1.0.dist-info/LICENSE-APACHE
pimage-1.1.0.dist-info/LICENSE-MIT
pimage-1.1.0.dist-info/METADATA
pimage-1.1.0.dist-info/WHEEL
pimage-1.1.0.dist-info/top_level.txt
pimage-1.1.0.dist-info/RECORD
