Metadata-Version: 2.1
Name: pimage
Version: 1.1.0
Summary: Library for detecting image copy-move attack
Author-email: Rahmat Nazali Salimi <rahmatnazali95@gmail.com>
Maintainer-email: Rahmat Nazali Salimi <rahmatnazali95@gmail.com>
Project-URL: Homepage, https://github.com/rahmatnazali/pimage
Project-URL: Bug Tracker, https://github.com/rahmatnazali/pimage/issues
Keywords: image,copy-move,attack,detection
Classifier: Development Status :: 4 - Beta
Classifier: Environment :: Console
Classifier: Intended Audience :: Developers
Classifier: Intended Audience :: Education
Classifier: Intended Audience :: Information Technology
Classifier: Intended Audience :: Science/Research
Classifier: License :: OSI Approved :: Apache Software License
Classifier: License :: OSI Approved :: MIT License
Classifier: Natural Language :: English
Classifier: Operating System :: OS Independent
Classifier: Programming Language :: Python :: 3 :: Only
Classifier: Topic :: Scientific/Engineering :: Image Processing
Requires-Python: >=3.8.10
License-File: LICENSE-APACHE
License-File: LICENSE-MIT
Requires-Dist: numpy (==1.24.1)
Requires-Dist: scikit-learn (==1.2.1)
Requires-Dist: tqdm (==4.64.1)
Requires-Dist: Pillow (==9.4.0)
Requires-Dist: imageio (==2.25.0)
